mbgdml/__init__.py
mbgdml/_version.py
mbgdml/alchemy.py
mbgdml/descriptors.py
mbgdml/logger.py
mbgdml/losses.py
mbgdml/mbe.py
mbgdml/periodic.py
mbgdml/stress.py
mbgdml/switching.py
mbgdml/train.py
mbgdml/utils.py
mbgdml/_gdml/__init__.py
mbgdml/_gdml/desc.py
mbgdml/_gdml/perm.py
mbgdml/_gdml/predict.py
mbgdml/_gdml/sample.py
mbgdml/_gdml/torchtools.py
mbgdml/_gdml/train.py
mbgdml/_gdml/solvers/__init__.py
mbgdml/_gdml/solvers/analytic.py
mbgdml/_gdml/solvers/iterative.py
mbgdml/active_learning/__init__.py
mbgdml/active_learning/drive_md.py
mbgdml/active_learning/sample_md.py
mbgdml/analysis/__init__.py
mbgdml/analysis/clustering.py
mbgdml/analysis/models.py
mbgdml/analysis/problematic.py
mbgdml/analysis/rdf.py
mbgdml/data/__init__.py
mbgdml/data/basedata.py
mbgdml/data/dataset.py
mbgdml/data/predictset.py
mbgdml/interfaces/__init__.py
mbgdml/interfaces/ase.py
mbgdml/models/__init__.py
mbgdml/models/base.py
mbgdml/models/gap_model.py
mbgdml/models/gdml_model.py
mbgdml/models/schnet_model.py
mbgdml/predictors/__init__.py
mbgdml/predictors/gap_predict.py
mbgdml/predictors/gdml_predict.py
mbgdml/predictors/schnet_predict.py
mbgdml/structure_gen/__init__.py
mbgdml/structure_gen/packmol_gen.py
mbgdml/structure_gen/utils.py
mbGDML-0.1.1.dist-info/LICENSE
mbGDML-0.1.1.dist-info/METADATA
mbGDML-0.1.1.dist-info/NOTICE
mbGDML-0.1.1.dist-info/WHEEL
mbGDML-0.1.1.dist-info/top_level.txt
mbGDML-0.1.1.dist-info/RECORD
