Metadata-Version: 2.1
Name: mbGDML
Version: 0.1.1
Summary: Create, use, and analyze machine learning potentials within the many-body expansion framework
Home-page: https://github.com/keithgroup/mbGDML
Author: Alex M. Maldonado
Author-email: aalexmmaldonado@gmail.com
License: MIT license
Classifier: Development Status :: 4 - Beta
Classifier: Intended Audience :: Science/Research
Classifier: License :: OSI Approved :: MIT License
Classifier: Natural Language :: English
Classifier: Programming Language :: Python :: 3
Classifier: Topic :: Scientific/Engineering
Classifier: Topic :: Scientific/Engineering :: Chemistry
Requires-Python: >=3.7
License-File: LICENSE
License-File: NOTICE
Requires-Dist: ase
Requires-Dist: cclib (>=1.7)
Requires-Dist: matplotlib
Requires-Dist: numpy
Requires-Dist: scipy
Requires-Dist: psutil
Requires-Dist: bayesian-optimization (>=1.4.0)
Requires-Dist: pandas
Requires-Dist: qcelemental (>=0.25.1)
Requires-Dist: pydantic (<2.0.0)
Requires-Dist: ray (>=2.0.0)
Requires-Dist: pytest
